py_handwrite/__init__.py
py_handwrite/images/+.png
"py_handwrite/images/,.png"
py_handwrite/images/-.png
py_handwrite/images/0.png
py_handwrite/images/1.png
py_handwrite/images/2.png
py_handwrite/images/3.png
py_handwrite/images/4.png
py_handwrite/images/5.png
py_handwrite/images/6.png
py_handwrite/images/7.png
py_handwrite/images/8.png
py_handwrite/images/9.png
py_handwrite/images/_.png
py_handwrite/images/_A.png
py_handwrite/images/_B.png
py_handwrite/images/_C.png
py_handwrite/images/_D.png
py_handwrite/images/_E.png
py_handwrite/images/_F.png
py_handwrite/images/_G.png
py_handwrite/images/_H.png
py_handwrite/images/_I.png
py_handwrite/images/_J.png
py_handwrite/images/_K.png
py_handwrite/images/_L.png
py_handwrite/images/_M.png
py_handwrite/images/_N.png
py_handwrite/images/_O.png
py_handwrite/images/_P.png
py_handwrite/images/_Q.png
py_handwrite/images/_R.png
py_handwrite/images/_S.png
py_handwrite/images/_T.png
py_handwrite/images/_U.png
py_handwrite/images/_V.png
py_handwrite/images/_W.png
py_handwrite/images/_X.png
py_handwrite/images/_Y.png
py_handwrite/images/_Z.png
py_handwrite/images/a.png
py_handwrite/images/b.png
py_handwrite/images/background.png
py_handwrite/images/c.png
py_handwrite/images/d.png
py_handwrite/images/e.png
py_handwrite/images/f.png
py_handwrite/images/g.png
py_handwrite/images/h.png
py_handwrite/images/i.png
py_handwrite/images/j.png
py_handwrite/images/k.png
py_handwrite/images/l.png
py_handwrite/images/m.png
py_handwrite/images/n.png
py_handwrite/images/o.png
py_handwrite/images/p.png
py_handwrite/images/q.png
py_handwrite/images/que.png
py_handwrite/images/r.png
py_handwrite/images/s.png
py_handwrite/images/t.png
py_handwrite/images/u.png
py_handwrite/images/v.png
py_handwrite/images/w.png
py_handwrite/images/x.png
py_handwrite/images/y.png
py_handwrite/images/z.png
py_handwrite-1.0.dist-info/METADATA
py_handwrite-1.0.dist-info/WHEEL
py_handwrite-1.0.dist-info/top_level.txt
py_handwrite-1.0.dist-info/RECORD
