Metadata-Version: 2.1
Name: py_handwrite
Version: 1.0
Summary: Convert Text to HandWritten Image
Author: Jenil sheth
Author-email: shethjeniljigneshbhai@gmail.com
Requires-Dist: pillow
